{
  "access_right": "open",
  "title": "11 Years of Research on Land and Freshwater Molluscs Along the Belgian Coast",
  "description": "<p>This project presents the analyses (in English) and a summary report (in Dutch) on 11 years of inventorying land and freshwater molluscs along the Belgian coast.<\/p>",
  "keywords": [
    "molluscs",
    "snails",
    "inventory",
    "dunes",
    "Flanders",
    "polders",
    "coast"
  ],
  "upload_type": "software",
  "license": "CC-BY-4.0",
  "language": "nld",
  "contributors": [
    {
      "name": "Langeraert, Ward",
      "affiliation": "Research Institute for Nature and Forest (INBO)",
      "orcid": "0000-0002-5900-8109",
      "type": "contactperson"
    },
    {
      "name": "Research Institute for Nature and Forest (INBO)",
      "type": "rightsholder"
    }
  ],
  "creators": [
    {
      "name": "Langeraert, Ward",
      "affiliation": "Research Institute for Nature and Forest (INBO)",
      "orcid": "0000-0002-5900-8109"
    }
  ],
  "communities": [
    {
      "identifier": "inbo"
    }
  ]
}
